Metadata-Version: 1.1
Name: django-logging-endpoint
Version: 1.0.4
Summary: Provide an endpoint to receive logs and push them to a configurable django logger
Home-page: https://github.com/propylon/django-logging-endpoint
Author: Propylon
Author-email: opensource@propylon.com
License: Apache-2.0
Platform: UNKNOWN
Classifier: Environment :: Web Environment
Classifier: Framework :: Django
Classifier: Framework :: Django :: 1.11
Classifier: Framework :: Django :: 2.2
Classifier: Intended Audience :: Developers
Classifier: License :: OSI Approved :: Apache Software License
Classifier: Operating System :: OS Independent
Classifier: Programming Language :: Python
Classifier: Programming Language :: Python :: 2.7
Classifier: Programming Language :: Python :: 3
Classifier: Programming Language :: Python :: 3.6
Classifier: Topic :: Internet :: WWW/HTTP
Classifier: Topic :: Internet :: WWW/HTTP :: Dynamic Content
